LICENSE
MANIFEST.in
README.rst
setup.py
NMCC_ACIS.egg-info/PKG-INFO
NMCC_ACIS.egg-info/SOURCES.txt
NMCC_ACIS.egg-info/dependency_links.txt
NMCC_ACIS.egg-info/top_level.txt
nmccacis/__init__.py
nmccacis/stndata/__init__.py
nmccacis/stndata/dailydata2pointsdatadict.py
nmccacis/stndata/dailydatalisting.py
nmccacis/stndata/dailydatatempgraph.py