Metadata-Version: 1.1
Name: NMCC-ACIS
Version: 0.0.2
Summary: A package that retrieves and formats ACIS data.
Home-page: https://bitbucket.org/nmclimate/nmcc-acis/
Author: Stanley Engle
Author-email: sengle@nmsu.edu
License: BSD
Platform: UNKNOWN
Classifier: Intended Audience :: Developers
Classifier: License :: OSI Approved :: BSD License
Classifier: Operating System :: OS Independent
Classifier: Programming Language :: Python
Classifier: Programming Language :: Python :: 2.6
Classifier: Programming Language :: Python :: 2.7
